HISTORY.rst
bypy/__init__.py
bypy/__main__.py
bypy/bypy.cacerts.pem
bypy/bypy.py
bypy/cached.py
bypy/chkreq.py
bypy/const.py
bypy/gui.py
bypy/gvar.py
bypy/monkey.py
bypy/panapi.py
bypy/printer.py
bypy/printer_console.py
bypy/printer_gui.py
bypy/printer_util.py
bypy/requester.py
bypy/struct.py
bypy/termcolor.py
bypy/tkutil.py
bypy/util.py
bypy/res/__init__.py
bypy/res/auth.json
bypy/test/__init__.py
bypy/test/__main__.py
bypy/test/test.py
bypy-1.8.9.dist-info/LICENSE
bypy-1.8.9.dist-info/METADATA
bypy-1.8.9.dist-info/WHEEL
bypy-1.8.9.dist-info/entry_points.txt
bypy-1.8.9.dist-info/top_level.txt
bypy-1.8.9.dist-info/RECORD
