Metadata-Version: 2.1
Name: bypy
Version: 1.8.9
Summary: Python client for Baidu Yun (Personal Cloud Storage) 百度云/百度网盘 Python 客户端
Home-page: https://github.com/houtianze/bypy
Download-URL: https://github.com/houtianze/bypy/tarball/1.8.9
Author: Hou Tianze
Author-email: houtianze@users.noreply.github.com
License: MIT
Keywords: bypy,bypy.py,baidu pcs,baidu yun,baidu pan,baidu netdisk,baidu cloud storage,baidu personal cloud storage,百度云,百度云盘,百度网盘,百度个人云存储
Classifier: Development Status :: 4 - Beta
Classifier: Environment :: Console
Classifier: Intended Audience :: End Users/Desktop
Classifier: Intended Audience :: Developers
Classifier: Intended Audience :: System Administrators
Classifier: License :: OSI Approved :: MIT License
Classifier: Natural Language :: English
Classifier: Operating System :: MacOS :: MacOS X
Classifier: Operating System :: Microsoft :: Windows
Classifier: Operating System :: POSIX
Classifier: Operating System :: Unix
Classifier: Programming Language :: Python
Classifier: Topic :: Utilities
Classifier: Topic :: Internet :: WWW/HTTP
License-File: LICENSE
Requires-Dist: multiprocess
Requires-Dist: requests
Requires-Dist: requests-toolbelt
